onnxprofile/__init__.py
onnxprofile/__main__.py
onnxprofile/commons.py
onnxprofile/operations.py
onnxprofile/profiler.py
onnxprofile/sparsity.py
onnxprofile/tensors.py
onnxprofile/hooks/__init__.py
onnxprofile/hooks/elementwise.py
onnxprofile/hooks/fusion.py
onnxprofile/hooks/pointwise.py
onnxprofile/hooks/quantize.py
onnxprofile/hooks/common/__init__.py
onnxprofile/hooks/common/constants.py
onnxprofile/hooks/common/functions.py
onnxprofile/hooks/common/utilities.py
onnxprofile-0.0.1.dist-info/LICENSE
onnxprofile-0.0.1.dist-info/METADATA
onnxprofile-0.0.1.dist-info/WHEEL
onnxprofile-0.0.1.dist-info/entry_points.txt
onnxprofile-0.0.1.dist-info/top_level.txt
onnxprofile-0.0.1.dist-info/zip-safe
onnxprofile-0.0.1.dist-info/RECORD
